{
   "players":{
      "86382033":{
         "id":"86382033",
         "score":"3",
         "color":"d6b156",
         "deck":"2",
         "card":"3",
         "cardname":"Dire Wolf",
         "text":"The Dire Wolf may do up to 2 combat moves.",
         "color_back":null,
         "name":"SunovaPeach",
         "avatar":"355fd1555a",
         "zombie":0,
         "eliminated":0,
         "is_ai":"0",
         "beginner":false
      },
      "90958523":{
         "id":"90958523",
         "score":"6",
         "color":"8ec459",
         "deck":"3",
         "card":"2",
         "cardname":"Charging Buck",
         "text":"The Charging Buck may do up to 2 combat leaps, each of distance exactly 2.",
         "color_back":null,
         "name":"BordGameFreak",
         "avatar":"_def_171",
         "zombie":0,
         "eliminated":0,
         "is_ai":"0",
         "beginner":false
      }
   },
   "game_form":"highform",
   "last_player":"0",
   "board":[
      {
         "x":"3",
         "y":"2",
         "player":"86382033",
         "rank":"1"
      },
      {
         "x":"3",
         "y":"3",
         "player":"86382033",
         "rank":"0"
      },
      {
         "x":"3",
         "y":"5",
         "player":"90958523",
         "rank":"1"
      },
      {
         "x":"4",
         "y":"1",
         "player":"86382033",
         "rank":"1"
      },
      {
         "x":"4",
         "y":"3",
         "player":"86382033",
         "rank":"0"
      },
      {
         "x":"4",
         "y":"7",
         "player":"90958523",
         "rank":"1"
      },
      {
         "x":"5",
         "y":"1",
         "player":"86382033",
         "rank":"0"
      },
      {
         "x":"5",
         "y":"2",
         "player":"86382033",
         "rank":"1"
      },
      {
         "x":"5",
         "y":"4",
         "player":"86382033",
         "rank":"2"
      },
      {
         "x":"5",
         "y":"7",
         "player":"90958523",
         "rank":"1"
      },
      {
         "x":"6",
         "y":"1",
         "player":"86382033",
         "rank":"0"
      },
      {
         "x":"6",
         "y":"6",
         "player":"90958523",
         "rank":"0"
      },
      {
         "x":"6",
         "y":"7",
         "player":"90958523",
         "rank":"0"
      },
      {
         "x":"7",
         "y":"3",
         "player":"86382033",
         "rank":"1"
      },
      {
         "x":"7",
         "y":"7",
         "player":"90958523",
         "rank":"0"
      }
   ],
   "hand":[
      {
         "id":"148",
         "type":"Flare",
         "type_arg":"5",
         "location":"hand",
         "location_arg":"90958523",
         "upgraded":"Place 1 common piece of your color on any empty square, or upgrade 1 of your common pieces.",
         "pieces":"You may do 1 combat leap with one of your common pieces."
      },
      {
         "id":"130",
         "type":"Legends",
         "type_arg":"10",
         "location":"hand",
         "location_arg":"90958523",
         "name":"Storm Elemental",
         "text":"You may place 1 piece of your color on an empty square up to distance 3. With it, do up to 1 (if legendary), 3 (if heroic), or 5 (if common) combat moves in one direction. Then destroy it."
      },
      {
         "id":"135",
         "type":"Legends",
         "type_arg":"6",
         "location":"hand",
         "location_arg":"90958523",
         "name":"Leviathan",
         "text":"Chose one: Either downgrade a connected group of up to 3 upgraded pieces or destroy a connected group of up to 4 common pieces. (A group may have multiple colors.)"
      },
      {
         "id":"137",
         "type":"Legends",
         "type_arg":"5",
         "location":"hand",
         "location_arg":"90958523",
         "name":"Fire Elemental",
         "text":"Destroy either all non-legendary enemy pieces on all adjacent squares or all common enemy pieces up to distance 2."
      },
      {
         "id":"57",
         "type":"Sylvan",
         "type_arg":"17",
         "location":"hand",
         "location_arg":"90958523",
         "name":"Tree Shepherd",
         "text":"Choose 1 of your pieces: If it is common, upgrade it; if heroic, it may do 1 combat move; if legendary, it may do 1 standard move."
      },
      {
         "id":"58",
         "type":"Sylvan",
         "type_arg":"16",
         "location":"hand",
         "location_arg":"90958523",
         "name":"Kiskin Boughrunner",
         "text":"The Kiskin Boughrunner may do up to 3 combat moves. Each move must end on a square adjacent to one of your pieces."
      },
      {
         "id":"69",
         "type":"Sylvan",
         "type_arg":"4",
         "location":"hand",
         "location_arg":"90958523",
         "name":"Naiad",
         "text":"You may choose up to 2 of your pieces adjacent to the Naiad and do 1 standard move with each."
      }
   ],
   "discard":[
      {
         "id":"55",
         "type":"Sylvan",
         "type_arg":"2",
         "location":"discard",
         "location_arg":"27",
         "name":"Charging Buck",
         "text":"The Charging Buck may do up to 2 combat leaps, each of distance exactly 2."
      },
      {
         "id":"56",
         "type":"Sylvan",
         "type_arg":"12",
         "location":"discard",
         "location_arg":"19",
         "name":"Woodland Druid",
         "text":"Upgrade 1 common piece of each color."
      },
      {
         "id":"59",
         "type":"Sylvan",
         "type_arg":"13",
         "location":"discard",
         "location_arg":"2",
         "name":"Forest Ancient",
         "text":"Place 2 enemy common pieces on empty squares up to distance 2. Then destroy 2 common pieces of the same color or colors up to distance 3."
      },
      {
         "id":"60",
         "type":"Sylvan",
         "type_arg":"5",
         "location":"discard",
         "location_arg":"1",
         "name":"Kiskin Spirit",
         "text":"You may choose a card from your discard pile and put it on top of your deck. If you do, or if your discard pile was empty, draw 1 extra card from your deck at the end of this turn."
      },
      {
         "id":"61",
         "type":"Sylvan",
         "type_arg":"0",
         "location":"discard",
         "location_arg":"22",
         "name":"Sapling",
         "text":"Upgrade the Sapling after summoning it."
      },
      {
         "id":"62",
         "type":"Sylvan",
         "type_arg":"8",
         "location":"discard",
         "location_arg":"16",
         "name":"Centaur Chieftain",
         "text":"The Centaur Chieftain may do 1 combat move. If he does, you may do up to 3 combat moves in the same direction, using other pieces of yours."
      },
      {
         "id":"66",
         "type":"Sylvan",
         "type_arg":"10",
         "location":"discard",
         "location_arg":"9",
         "name":"Sylvan Queen",
         "text":"You may convert 1 non-legendary enemy piece on a diagonally adjacent square to your piece of the same rank."
      },
      {
         "id":"67",
         "type":"Sylvan",
         "type_arg":"14",
         "location":"discard",
         "location_arg":"8",
         "name":"Forest Mystic",
         "text":"At the end of this turn, draw 1 extra card from your deck and 1 extra card from the legendary deck."
      },
      {
         "id":"68",
         "type":"Sylvan",
         "type_arg":"9",
         "location":"discard",
         "location_arg":"3",
         "name":"Unicorn",
         "text":"Choose one: Either the Unicorn may do 1 combat move, or you gain 1 action."
      },
      {
         "id":"70",
         "type":"Sylvan",
         "type_arg":"7",
         "location":"discard",
         "location_arg":"26",
         "name":"Centaur Spearman",
         "text":"The Centaur Spearman may do 1 combat move. If he does, destroy the next piece in the same direction, unless it is legendary."
      },
      {
         "id":"71",
         "type":"Sylvan",
         "type_arg":"3",
         "location":"discard",
         "location_arg":"14",
         "name":"Forest Wardens",
         "text":"Destroy 1 common piece of an opponent with more common pieces than you. Destroy 1 heroic piece of an opponent with more upgraded pieces than you."
      },
      {
         "id":"72",
         "type":"Sylvan",
         "type_arg":"11",
         "location":"discard",
         "location_arg":"4",
         "name":"Sylvan Princess",
         "text":"You may convert 1 common enemy piece on a diagonally adjacent square to your common piece."
      }
   ],
   "current_tasks":{
      "154":{
         "id":"154",
         "type":"task",
         "type_arg":"6",
         "location":"current_tasks",
         "location_arg":"0",
         "name":"Green Conquest",
         "text":"You have at least 3 pieces on green squares, and at least 2 of them are upgraded."
      },
      "159":{
         "id":"159",
         "type":"task",
         "type_arg":"19",
         "location":"current_tasks",
         "location_arg":"0",
         "name":"Side Chain",
         "text":"Squares on two opposite sides of the board are connected by a chain of your pieces."
      },
      "169":{
         "id":"169",
         "type":"task",
         "type_arg":"23",
         "location":"current_tasks",
         "location_arg":"0",
         "name":"Isolation",
         "text":"An enemy piece is within 2 squares of another enemy piece, but it cannot get adjacent to any enemy piece in 3 or fewer moves through empty squares."
      }
   },
   "next_task":{
      "161":{
         "id":"161",
         "type":"task",
         "type_arg":"21",
         "location":"next_task",
         "location_arg":"0",
         "name":"Imprisonment",
         "text":"You have at least 6 pieces adjacent to the same enemy piece."
      }
   },
   "claimed":{
      "86382033":{
         "168":{
            "id":"168",
            "type":"task",
            "type_arg":"2",
            "location":"claimed",
            "location_arg":"86382033",
            "name":"Heroic Destruction",
            "text":"You destroyed at least 3 enemy pieces this turn, at least 1 of them upgraded."
         }
      },
      "90958523":{
         "151":{
            "id":"151",
            "type":"task",
            "type_arg":"1",
            "location":"claimed",
            "location_arg":"90958523",
            "name":"Devastation",
            "text":"You destroyed at least 4 enemy pieces this turn."
         },
         "160":{
            "id":"160",
            "type":"task",
            "type_arg":"22",
            "location":"claimed",
            "location_arg":"90958523",
            "name":"Envelopment",
            "text":"You have at least 7 pieces adjacent to the same enemy piece."
         },
         "171":{
            "id":"171",
            "type":"task",
            "type_arg":"16",
            "location":"claimed",
            "location_arg":"90958523",
            "name":"Center Cross",
            "text":"You have at least 5 pieces on the central squares in a + or x pattern."
         }
      }
   },
   "card_x":"4",
   "card_y":"3",
   "differentials":{
      "player_id":"90958523",
      "player_name":"BordGameFreak",
      "player_no":"2",
      "player_avatar":"_def_171",
      "player_color":"8ec459",
      "player_canal":"c90766a1a952f9c48c32d631e939584c",
      "player_is_admin":"0",
      "player_zombie":0,
      "player_eliminated":0,
      "player_next_notif_no":"1",
      "player_enter_game":"1",
      "player_ai":"0",
      "player_beginner":null,
      "concede":0,
      "upgraded":3,
      "pieces":6,
      "legendary":0,
      "args":{
         "nonlegendary_86382033":9,
         "legendary_86382033":2,
         "cards_86382033":"2",
         "upgradeddiff_vs_d6b156":2,
         "piecesdiff_vs_d6b156":3,
         "nonlegendary_90958523":11,
         "legendary_90958523":3,
         "cards_90958523":"3",
         "activable":false,
         "flarenum":"5"
      }
   },
   "before":"0",
   "after":0,
   "destroyed_args":{
      "game_form":"1",
      "scores_dm":{
         "86382033":{
            "90958523":{
               "id":"86382033",
               "against":"90958523",
               "value":"0",
               "common":"0",
               "heroic":"0",
               "legendary":"0",
               "impro":"0"
            }
         },
         "90958523":{
            "86382033":{
               "id":"90958523",
               "against":"86382033",
               "value":"0",
               "common":"0",
               "heroic":"0",
               "legendary":"0",
               "impro":"0"
            }
         }
      }
   },
   "frozen":"-1",
   "pending":"-1",
   "gateway_x":"-1",
   "gateway_y":"-1",
   "turn_counter":"11",
   "merchant_player":"0",
   "merchant_rank":"0",
   "gamestate":{
      "id":"21",
      "active_player":"90958523",
      "args":{
         "discard_ok":true,
         "empty":{
            "1":{
               "3":null,
               "4":null,
               "5":null,
               "6":null,
               "7":null
            },
            "2":{
               "2":null,
               "3":null,
               "4":null,
               "5":null,
               "6":null,
               "7":null,
               "8":null
            },
            "3":{
               "1":null,
               "4":null,
               "6":null,
               "7":null,
               "8":null,
               "9":null
            },
            "4":{
               "2":null,
               "4":null,
               "5":null,
               "6":null,
               "8":null,
               "9":null
            },
            "5":{
               "3":null,
               "5":null,
               "6":null,
               "8":null,
               "9":null
            },
            "6":{
               "2":null,
               "3":null,
               "4":null,
               "5":null,
               "8":null,
               "9":null
            },
            "7":{
               "1":null,
               "2":null,
               "4":null,
               "5":null,
               "6":null,
               "8":null,
               "9":null
            },
            "8":{
               "2":null,
               "3":null,
               "4":null,
               "5":null,
               "6":null,
               "7":null,
               "8":null
            },
            "9":{
               "3":null,
               "4":null,
               "5":null,
               "6":null,
               "7":null
            }
         },
         "actions":"2",
         "frozen":"-1",
         "pending":"-1",
         "turn_counter":"11"
      },
      "reflexion":{
         "total":{
            "86382033":"258638",
            "90958523":258669
         }
      },
      "updateGameProgression":87
   },
   "tablespeed":"17",
   "game_result_neutralized":"0",
   "neutralized_player_id":"0",
   "playerorder":[
      "90958523",
      86382033
   ],
   "gamestates":{
      "1":{
         "name":"gameSetup",
         "description":"Game setup",
         "type":"manager",
         "action":"stGameSetup",
         "transitions":{
            "":5
         }
      },
      "5":{
         "name":"randomDecks",
         "description":"",
         "type":"game",
         "action":"stRandomDecks",
         "transitions":{
            "beginGame":20,
            "chooseDecks":10,
            "initialPiecesDuel":16,
            "initialPiecesMelee":17
         }
      },
      "10":{
         "name":"deckChoice",
         "description":"${actplayer} must choose a school",
         "descriptionmyturn":"${you} must choose a school",
         "type":"activeplayer",
         "args":"argDeckChoice",
         "possibleactions":[
            "chooseDeck"
         ],
         "transitions":{
            "chooseDeck":15,
            "zombiePass":99
         }
      },
      "15":{
         "name":"nextDeck",
         "description":"",
         "type":"game",
         "action":"stNextDeck",
         "transitions":{
            "beginGame":20,
            "nextDeck":10,
            "initialPiecesDuel":16,
            "initialPiecesMelee":17
         }
      },
      "16":{
         "name":"initialPiecesDuel",
         "description":"${actplayer} must place the initial pieces",
         "descriptionmyturn":"${you} must place one of your pieces on a square marked <div id=\"DMmark\"><\/div>",
         "type":"activeplayer",
         "possibleactions":[
            "placeInitialPieces"
         ],
         "transitions":{
            "placeInitialPieces":19,
            "zombiePass":20
         }
      },
      "17":{
         "name":"initialPiecesMelee",
         "description":"${actplayer} must place the initial pieces",
         "descriptionmyturn":"${you} must place a ${color} piece on a square adjacent to a <div id=\"DMMmark\"><\/div> symbol",
         "type":"activeplayer",
         "args":"argMeleeInitial",
         "possibleactions":[
            "placeInitialPieces",
            "placeLastPiece"
         ],
         "transitions":{
            "placeInitialPieces":17,
            "placeLastPiece":19,
            "zombiePass":20
         }
      },
      "19":{
         "name":"setFirstPlayer",
         "description":"",
         "type":"game",
         "action":"stSetFirstPlayer",
         "transitions":{
            "":20
         }
      },
      "20":{
         "name":"turnBegin",
         "description":"",
         "type":"game",
         "action":"stTurnBegin",
         "transitions":{
            "firstAction":21
         }
      },
      "21":{
         "name":"actionChoice",
         "description":"${actplayer} must play a piece or select a card (${actions} actions left)",
         "descriptionmyturn":"${you} must play a piece or select a card (${actions} actions left)",
         "type":"activeplayer",
         "args":"argActionChoice",
         "updateGameProgression":true,
         "possibleactions":[
            "playPiece",
            "playCard",
            "discardCard",
            "playFlare",
            "playFrozen",
            "playWarp",
            "pieceShortage",
            "browseHistory"
         ],
         "transitions":{
            "playPiece":70,
            "playCard":40,
            "chooseColorImpro":36,
            "chooseColorLegend":38,
            "discardCard":70,
            "chooseColorFlare":28,
            "playFlare":30,
            "playFrozen":40,
            "playWarp":40,
            "pieceShortage":22,
            "browseHistory":95,
            "zombiePass":70
         }
      },
      "22":{
         "name":"pickPiece",
         "description":"${actplayer} has no pieces left and must pick one up",
         "descriptionmyturn":"${you} have no pieces left and must pick one up",
         "type":"activeplayer",
         "args":"argPickPiece",
         "possibleactions":[
            "playPiece",
            "playCard",
            "cancelPick",
            "browseHistory"
         ],
         "transitions":{
            "playPiece":70,
            "playCard":40,
            "chooseColorLegend":38,
            "cancelPick":21,
            "browseHistory":95,
            "zombiePass":70
         }
      },
      "28":{
         "name":"chooseColorFlare",
         "description":"${actplayer} must choose against which color the flare is invoked",
         "descriptionmyturn":"${you} must choose against which color the flare is invoked",
         "type":"activeplayer",
         "args":"argChooseColorFlare",
         "possibleactions":[
            "colorChosen",
            "browseHistory"
         ],
         "transitions":{
            "colorChosen":30,
            "browseHistory":95,
            "zombiePass":50
         }
      },
      "30":{
         "name":"initFlare",
         "description":"",
         "type":"game",
         "action":"stInitFlare",
         "transitions":{
            "flareInitiated":50,
            "flaresDone":21,
            "flaresTurnDoneHF":75,
            "flaresTurnDoneDM":76
         }
      },
      "36":{
         "name":"chooseColorImpro",
         "description":"${actplayer} must choose a color for improvised summoning",
         "descriptionmyturn":"${you} must choose a color for improvised summoning",
         "type":"activeplayer",
         "args":"argChooseColorImpro",
         "possibleactions":[
            "playPiece",
            "playCard",
            "cancelPick",
            "browseHistory"
         ],
         "transitions":{
            "playCard":40,
            "chooseColorLegend":38,
            "pieceShortage":22,
            "browseHistory":95,
            "zombiePass":70
         }
      },
      "38":{
         "name":"chooseColorLegend",
         "description":"${actplayer} must choose a color to score the legend in",
         "descriptionmyturn":"${you} must choose a color to score your legend in",
         "type":"activeplayer",
         "args":"argChooseColorLegend",
         "possibleactions":[
            "colorChosen",
            "browseHistory"
         ],
         "transitions":{
            "colorChosen":40,
            "autoEffect":50,
            "browseHistory":95,
            "zombiePass":70
         }
      },
      "40":{
         "name":"initEffect",
         "description":"",
         "type":"game",
         "action":"stInitEffect",
         "transitions":{
            "effectsInitiated":50
         }
      },
      "41":{
         "name":"cardChoice",
         "description":"${actplayer} must choose a card",
         "descriptionmyturn":"${you} must choose a card",
         "type":"activeplayer",
         "args":"argCardChoice",
         "possibleactions":[
            "effectPlayed",
            "skip",
            "browseHistory"
         ],
         "transitions":{
            "effectPlayed":50,
            "skip":50,
            "browseHistory":95,
            "zombiePass":50
         }
      },
      "42":{
         "name":"squareChoice",
         "description":"${actplayer} must choose a square",
         "descriptionmyturn":"${you} must choose a square",
         "type":"activeplayer",
         "args":"argPlaceInput",
         "possibleactions":[
            "effectPlayed",
            "skip",
            "browseHistory"
         ],
         "transitions":{
            "effectPlayed":50,
            "skip":50,
            "browseHistory":95,
            "zombiePass":50
         }
      },
      "43":{
         "name":"pieceChoice",
         "description":"${actplayer} must choose a square",
         "descriptionmyturn":"${you} must choose a square",
         "type":"activeplayer",
         "args":"argEffectInput",
         "possibleactions":[
            "effectPlayed",
            "skip",
            "browseHistory"
         ],
         "transitions":{
            "effectPlayed":50,
            "skip":50,
            "browseHistory":95,
            "zombiePass":50
         }
      },
      "44":{
         "name":"moveChoice",
         "description":"${actplayer} must move a piece",
         "descriptionmyturn":"${you} must move a piece",
         "type":"activeplayer",
         "args":"argEffectInput",
         "possibleactions":[
            "effectPlayed",
            "skip",
            "browseHistory"
         ],
         "transitions":{
            "effectPlayed":50,
            "skip":50,
            "browseHistory":95,
            "zombiePass":50
         }
      },
      "45":{
         "name":"directionChoice",
         "description":"${actplayer} must choose a direction",
         "descriptionmyturn":"${you} must choose a direction",
         "type":"activeplayer",
         "args":"argEffectInput",
         "possibleactions":[
            "effectPlayed",
            "skip",
            "browseHistory"
         ],
         "transitions":{
            "effectPlayed":50,
            "skip":50,
            "browseHistory":95,
            "zombiePass":50
         }
      },
      "46":{
         "name":"orEffects2",
         "description":"${actplayer} must choose an effect",
         "descriptionmyturn":"${you} must choose an effect",
         "type":"activeplayer",
         "args":"argEffectInput",
         "possibleactions":[
            "effectPlayed",
            "skip",
            "browseHistory"
         ],
         "transitions":{
            "effectPlayed":50,
            "skip":50,
            "browseHistory":95,
            "zombiePass":50
         }
      },
      "47":{
         "name":"orEffects3",
         "description":"${actplayer} must choose an effect",
         "descriptionmyturn":"${you} must choose an effect",
         "type":"activeplayer",
         "args":"argEffectInput",
         "possibleactions":[
            "effectPlayed",
            "skip",
            "browseHistory"
         ],
         "transitions":{
            "effectPlayed":50,
            "skip":50,
            "browseHistory":95,
            "zombiePass":50
         }
      },
      "48":{
         "name":"chooseOption",
         "description":"${questionhe}",
         "descriptionmyturn":"${questionyou}",
         "type":"activeplayer",
         "args":"argOptions",
         "possibleactions":[
            "effectPlayed",
            "skip",
            "browseHistory"
         ],
         "transitions":{
            "effectPlayed":50,
            "skip":50,
            "browseHistory":95,
            "zombiePass":50
         }
      },
      "50":{
         "name":"nextEffect",
         "description":"",
         "type":"game",
         "action":"stNextEffect",
         "transitions":{
            "effectCard":41,
            "effectSquare":42,
            "effectPiece":43,
            "effectMovePiece":44,
            "effectDirection":45,
            "orEffects2":46,
            "orEffects3":47,
            "effectChoose":48,
            "autoEffect":50,
            "effectFalse":50,
            "chooseColorLegend":38,
            "chooseFrozen":55,
            "effectsDone":70,
            "nextFlare":30
         }
      },
      "55":{
         "name":"frozenChoice",
         "description":"${actplayer} must choose a frozen effect to put into play",
         "descriptionmyturn":"${you} must choose a frozen effect to put into play",
         "type":"activeplayer",
         "args":"argFrozenChoice",
         "possibleactions":[
            "frozenChosen",
            "browseHistory"
         ],
         "transitions":{
            "frozenChosen":70,
            "browseHistory":95,
            "zombiePass":70
         }
      },
      "70":{
         "name":"nextAction",
         "description":"",
         "type":"game",
         "action":"stNextAction",
         "transitions":{
            "nextAction":21,
            "actionsDoneHF":75,
            "actionsDoneDM":76
         }
      },
      "75":{
         "name":"turnEndHF",
         "description":"${actplayer} may invoke a flare or claim a task",
         "descriptionmyturn":"${you} may invoke a flare, claim a task or",
         "type":"activeplayer",
         "args":"argTurnEnd",
         "possibleactions":[
            "playFlare",
            "playFrozen",
            "playWarp",
            "chooseTask",
            "skip",
            "browseHistory"
         ],
         "transitions":{
            "chooseColorFlare":28,
            "playFlare":30,
            "playFrozen":40,
            "playWarp":40,
            "chooseTask":90,
            "skip":90,
            "browseHistory":95,
            "zombiePass":90
         }
      },
      "76":{
         "name":"turnEndDM",
         "description":"${actplayer} may invoke a flare",
         "descriptionmyturn":"${you} may invoke a flare or",
         "type":"activeplayer",
         "args":"argTurnEnd",
         "possibleactions":[
            "playFlare",
            "playFrozen",
            "playWarp",
            "skip",
            "chooseColor",
            "browseHistory"
         ],
         "transitions":{
            "chooseColorFlare":28,
            "playFlare":30,
            "playFrozen":40,
            "playWarp":40,
            "skip":90,
            "chooseColor":88,
            "browseHistory":95,
            "zombiePass":90
         }
      },
      "88":{
         "name":"chooseColor",
         "description":"${actplayer} must choose a color to score the unpaired pieces in",
         "descriptionmyturn":"${you} must choose a color to score your unpaired pieces in",
         "type":"activeplayer",
         "args":"argChooseColor",
         "possibleactions":[
            "colorChosen",
            "browseHistory"
         ],
         "transitions":{
            "colorChosen":90,
            "browseHistory":95,
            "zombiePass":90
         }
      },
      "90":{
         "name":"nextPlayer",
         "description":"",
         "type":"game",
         "action":"stNextPlayer",
         "transitions":{
            "nextPlayer":20,
            "endGame":99
         }
      },
      "95":{
         "name":"browseHistory",
         "description":"",
         "type":"game",
         "action":"stBrowseHistory",
         "transitions":{
            "actionChoice":21,
            "pickPiece":22,
            "chooseColorFlare":28,
            "chooseColorImpro":36,
            "chooseColorLegend":38,
            "effectCard":41,
            "effectSquare":42,
            "effectPiece":43,
            "effectMovePiece":44,
            "effectDirection":45,
            "orEffects2":46,
            "orEffects3":47,
            "effectChoose":48,
            "frozenChoice":55,
            "turnEndHF":75,
            "turnEndDM":76
         }
      },
      "99":{
         "name":"gameEnd",
         "description":"End of game",
         "type":"manager",
         "action":"stGameEnd",
         "args":"argGameEnd"
      }
   },
   "notifications":{
      "last_packet_id":"738",
      "move_nbr":"246"
   }
}